rabbit_broker/__init__.py
rabbit_broker/models.py
rabbit_broker/schemas.py
rabbit_broker/settings.py
rabbit_broker/async_chains/__init__.py
rabbit_broker/async_chains/base.py
rabbit_broker/chains/__init__.py
rabbit_broker/chains/base.py
rabbit_broker/queues/__init__.py
rabbit_broker/queues/base.py
rabbit_broker/queues/rabbitmq.py
rabbit_broker/services/__init__.py
rabbit_broker/services/base.py
rabbit_broker/utils/__init__.py
rabbit_broker/utils/singleton.py
rabbit_broker_test-0.0.5.dist-info/METADATA
rabbit_broker_test-0.0.5.dist-info/WHEEL
rabbit_broker_test-0.0.5.dist-info/licenses/LICENSE
rabbit_broker_test-0.0.5.dist-info/RECORD
